{
  "id": "dragonite",
  "name": "Dragonite",
  "image": "/placeholder.svg?height=80&width=80",
  "initialMove": "🪨 Trampa Rocas 🪨",
  "tricks": [
    {
      "detail": "Blaziken ➜ Slowbro , Bostezo ➜ Frente a Maractus 🔔Mira Abajo 🔔 ",
      "variant": [
        {
          "detail": "Rápido ➜ Sacrifica a Politoed ➜ Poliwrath +6🐸🥊 🔔(Puño drenaje Magmortar)🔔",
          "variant": []
        },
        {
          "detail": "Ahorrar dinero ➜ Entrar con Volcarona x3 Danza aleteo",
          "variant": []
        }
      ]
    },
    {
      "detail": "Bouffalant ➜ Gengar usa Maquinación ➜ Si entra Dragonite eliminalo con bola sombra",
      "variant": [
        {
          "detail": "Magmortar ➜ Sacrifica a Politoed ➜ Poliwrath +6🐸🥊 🔔(Puño drenaje contra Magmortar)🔔",
          "variant": []
        },
        {
          "detail": "Steelix ➜  Slowbro , Bostezo ➜ sacrifica a Politoed ➜ Poliwrath +6🐸🥊 🔔(Puño drenaje contra Magmortar)🔔",
          "variant": [
            {
              "detail": "🚨Arriesgado🚨 ➜ Sacrifica a Politoed ➜ Poliwrath +6🐸🥊",
              "variant": []
            }
          ]
        }
      ]   
    }
  ]   
}  
